py1kgp/__init__.py
py1kgp/py1kgp.py
py1kgp-0.1.2.dist-info/LICENSE
py1kgp-0.1.2.dist-info/METADATA
py1kgp-0.1.2.dist-info/WHEEL
py1kgp-0.1.2.dist-info/top_level.txt
py1kgp-0.1.2.dist-info/RECORD
