Metadata-Version: 2.1
Name: py1kgp
Version: 0.1.2
Summary: Utilities for working with 1000 Genomes data
Home-page: https://gitlab.com/aaylward/py1kgp
Author: Anthony Aylward
Author-email: aaylward@salk.edu
License: UNKNOWN
Platform: UNKNOWN
Classifier: Programming Language :: Python :: 3
Classifier: License :: OSI Approved :: MIT License
Classifier: Operating System :: OS Independent
License-File: LICENSE
Requires-Dist: pyhg19
